pygeai/__init__.py
pygeai/admin/__init__.py
pygeai/admin/clients.py
pygeai/admin/endpoints.py
pygeai/assistant/__init__.py
pygeai/assistant/clients.py
pygeai/assistant/endpoints.py
pygeai/assistant/managers.py
pygeai/assistant/mappers.py
pygeai/assistant/data/__init__.py
pygeai/assistant/data/clients.py
pygeai/assistant/data_analyst/__init__.py
pygeai/assistant/data_analyst/clients.py
pygeai/assistant/data_analyst/endpoints.py
pygeai/assistant/rag/__init__.py
pygeai/assistant/rag/clients.py
pygeai/assistant/rag/endpoints.py
pygeai/assistant/rag/mappers.py
pygeai/assistant/rag/models.py
pygeai/assistant/rag/responses.py
pygeai/chat/__init__.py
pygeai/chat/clients.py
pygeai/chat/endpoints.py
pygeai/chat/iris.py
pygeai/chat/managers.py
pygeai/chat/session.py
pygeai/chat/settings.py
pygeai/chat/ui.py
pygeai/cli/__init__.py
pygeai/cli/__main__.py
pygeai/cli/geai.py
pygeai/cli/geai_proxy.py
pygeai/cli/install_man.py
pygeai/cli/parsers.py
pygeai/cli/commands/__init__.py
pygeai/cli/commands/admin.py
pygeai/cli/commands/assistant.py
pygeai/cli/commands/base.py
pygeai/cli/commands/builders.py
pygeai/cli/commands/chat.py
pygeai/cli/commands/common.py
pygeai/cli/commands/configuration.py
pygeai/cli/commands/embeddings.py
pygeai/cli/commands/evaluation.py
pygeai/cli/commands/feedback.py
pygeai/cli/commands/files.py
pygeai/cli/commands/gam.py
pygeai/cli/commands/llm.py
pygeai/cli/commands/migrate.py
pygeai/cli/commands/options.py
pygeai/cli/commands/organization.py
pygeai/cli/commands/rag.py
pygeai/cli/commands/rerank.py
pygeai/cli/commands/secrets.py
pygeai/cli/commands/usage_limits.py
pygeai/cli/commands/validators.py
pygeai/cli/commands/version.py
pygeai/cli/commands/flows/__init__.py
pygeai/cli/commands/lab/__init__.py
pygeai/cli/commands/lab/ai_lab.py
pygeai/cli/commands/lab/common.py
pygeai/cli/commands/lab/options.py
pygeai/cli/commands/lab/spec.py
pygeai/cli/commands/lab/utils.py
pygeai/cli/texts/__init__.py
pygeai/cli/texts/help.py
pygeai/core/__init__.py
pygeai-0.4.0.dist-info/licenses/LICENSE
pygeai-0.4.0.dist-info/METADATA
pygeai-0.4.0.dist-info/WHEEL
pygeai-0.4.0.dist-info/entry_points.txt
pygeai-0.4.0.dist-info/top_level.txt
pygeai-0.4.0.dist-info/RECORD
