Metadata-Version: 2.4
Name: pygeai
Version: 0.4.0
Summary: Software Development Kit to interact with Globant Enterprise AI.
Author-email: Globant <geai-sdk@globant.com>
License-Expression: MIT
Keywords: geai,pygeai
Classifier: Development Status :: 5 - Production/Stable
Classifier: Intended Audience :: Developers
Classifier: Topic :: Software Development :: Libraries
Classifier: Programming Language :: Python :: 3
Classifier: Operating System :: OS Independent
Classifier: Development Status :: 4 - Beta
Requires-Python: >=3.10
License-File: LICENSE
Requires-Dist: requests
Requires-Dist: pydantic>=2.11.3
Requires-Dist: packaging
Requires-Dist: mcp
Requires-Dist: pyyaml
Requires-Dist: prompt_toolkit
Requires-Dist: toml
Requires-Dist: httpx==0.28.1
Requires-Dist: httpx-sse>=0.4.0
Requires-Dist: opentelemetry-api>=1.33.0
Requires-Dist: opentelemetry-sdk>=1.33.0
Requires-Dist: sse-starlette>=2.3.3
Requires-Dist: starlette>=0.46.2
Requires-Dist: typing-extensions>=4.13.2
Requires-Dist: streamlit
Provides-Extra: docs
Requires-Dist: sphinx; extra == "docs"
Requires-Dist: sphinx-rtd-theme; extra == "docs"
Requires-Dist: sphinx-markdown-builder; extra == "docs"
Provides-Extra: tests
Requires-Dist: coverage; extra == "tests"
Dynamic: license-file
